subprocess_alive/LICENSE
subprocess_alive/README.md
subprocess_alive/__init__.py
subprocess_alive/requirements.txt
subprocess_alive/thirdparty.json
subprocess_alive-0.10.dist-info/LICENSE.rst
subprocess_alive-0.10.dist-info/METADATA
subprocess_alive-0.10.dist-info/WHEEL
subprocess_alive-0.10.dist-info/top_level.txt
subprocess_alive-0.10.dist-info/RECORD
