Metadata-Version: 2.1
Name: subprocess-alive
Version: 0.10
Summary: Checks if a process (pid) is alive on Windows
Home-page: https://github.com/hansalemaos/subprocess_alive
Author: Johannes Fischer
Author-email: aulasparticularesdealemaosp@gmail.com
License: MIT
Keywords: pid,isalive
Classifier: Development Status :: 4 - Beta
Classifier: Programming Language :: Python :: 3 :: Only
Classifier: Programming Language :: Python :: 3.10
Classifier: Topic :: Software Development :: Libraries :: Python Modules
Classifier: Topic :: Utilities
License-File: LICENSE.rst
Requires-Dist: comtypes
